README.txt
setup.py
zbx_statsd.egg-info/PKG-INFO
zbx_statsd.egg-info/SOURCES.txt
zbx_statsd.egg-info/dependency_links.txt
zbx_statsd.egg-info/entry_points.txt
zbx_statsd.egg-info/requires.txt
zbx_statsd.egg-info/top_level.txt
zbxstatsd/__init__.py
zbxstatsd/client.py
zbxstatsd/daemon.py
zbxstatsd/server.py