Metadata-Version: 1.0
Name: zbx-statsd
Version: 0.4.0
Summary: Clone of Etsy's statsd and Steve Ivy's py-statsd designed to work with Zabbix (http://www.zabbix.com/).
Home-page: https://github.com/pistolero/zbx-statsd
Author: Sergey Kirillov
Author-email: sergey.kirillov@gmail.com
License: BSD
Platform: UNKNOWN
Classifier: License :: OSI Approved :: BSD License
